arp_jarvis_atomic_nodes-0.3.8.dist-info/licenses/LICENSE
jarvis_atomic_nodes/__init__.py
jarvis_atomic_nodes/catalog.py
jarvis_atomic_nodes/core_nodes.py
jarvis_atomic_nodes/discovery.py
jarvis_atomic_nodes/handlers.py
jarvis_atomic_nodes/http_nodes.py
jarvis_atomic_nodes/pack.py
jarvis_atomic_nodes/sdk.py
arp_jarvis_atomic_nodes-0.3.8.dist-info/METADATA
arp_jarvis_atomic_nodes-0.3.8.dist-info/WHEEL
arp_jarvis_atomic_nodes-0.3.8.dist-info/entry_points.txt
arp_jarvis_atomic_nodes-0.3.8.dist-info/top_level.txt
arp_jarvis_atomic_nodes-0.3.8.dist-info/RECORD
