Metadata-Version: 2.4
Name: arp-jarvis-atomic-nodes
Version: 0.3.8
Summary: First-party atomic node pack for the JARVIS stack (metadata + handlers).
Author: Agent Runtime Protocol
License-Expression: MIT
Requires-Python: >=3.11
License-File: LICENSE
Requires-Dist: arp-standard-model==0.3.7
Provides-Extra: metadata
Provides-Extra: runtime
Requires-Dist: httpx>=0.27.0; extra == "runtime"
Provides-Extra: dev
Requires-Dist: pyright>=1.1.0; extra == "dev"
Requires-Dist: pytest>=7; extra == "dev"
Requires-Dist: httpx>=0.27.0; extra == "dev"
Dynamic: license-file
